libtimed/__init__.py
libtimed/models.py
libtimed/oidc.py
libtimed/transforms.py
libtimed-0.6.5.dist-info/LICENSE
libtimed-0.6.5.dist-info/METADATA
libtimed-0.6.5.dist-info/WHEEL
libtimed-0.6.5.dist-info/RECORD
