Metadata-Version: 2.1
Name: libtimed
Version: 0.6.5
Summary: Library to intreact with timed webapp.
Author: Arthur Deierlein
Author-email: arthur.deierlein@adfinis.com
Requires-Python: >=3.10,<4.0
Classifier: Programming Language :: Python :: 3
Classifier: Programming Language :: Python :: 3.10
Classifier: Programming Language :: Python :: 3.11
Classifier: Programming Language :: Python :: 3.12
Requires-Dist: inflection (>=0.5.1,<0.6.0)
Requires-Dist: keyring (>=24.1.0,<25.0.0)
Requires-Dist: requests (>=2.31.0,<3.0.0)
Requires-Dist: requests-cache (>=1.1.0,<2.0.0)
